pytest_deprecator/__init__.py
pytest_deprecator/plugin.py
pytest_deprecator-0.0.1.dist-info/METADATA
pytest_deprecator-0.0.1.dist-info/WHEEL
pytest_deprecator-0.0.1.dist-info/entry_points.txt
pytest_deprecator-0.0.1.dist-info/top_level.txt
pytest_deprecator-0.0.1.dist-info/RECORD
